repositorytest-0.4.6.dist-info/licenses/LICENSE
repotest/__init__.py
repotest/constants.env
repotest/constants.py
repotest/logger.py
repotest/cli/__init__.py
repotest/cli/liveswebench.py
repotest/core/__init__.py
repotest/core/base.py
repotest/core/exceptions.py
repotest/core/docker/__init__.py
repotest/core/docker/base.py
repotest/core/docker/java.py
repotest/core/docker/python.py
repotest/core/local/__init__.py
repotest/core/local/base.py
repotest/core/local/java.py
repotest/core/local/python.py
repotest/manager/__init__.py
repotest/manager/java_testgen_task_manager.py
repotest/manager/liveswebench_task_collector_manager.py
repotest/manager/liveswebench_task_manager.py
repotest/manager/realcode_java_task_manager.py
repotest/manager/realcode_python_task_manager.py
repotest/manager/realcode_task_collector_manager.py
repotest/parsers/__init__.py
repotest/parsers/java/__init__.py
repotest/parsers/java/jacoco_report.py
repotest/parsers/java/maven_stdout.py
repotest/parsers/java/surefire_report.py
repotest/parsers/python/__init__.py
repotest/parsers/python/collect_task.py
repotest/parsers/python/pytest_stdout.py
repotest/scripts/__init__.py
repotest/scripts/build_image.py
repotest/scripts/check_instalation.py
repotest/scripts/check_perfomance.py
repotest/scripts/java_cov_v2.py
repotest/scripts/save_realcode_input_ecs_gigacode_worker.py
repotest/utils/__init__.py
repotest/utils/timeout.py
repotest/utils/clean/__init__.py
repotest/utils/dataset/__init__.py
repotest/utils/dataset/_add_command_column_to_dataset_v2.py
repotest/utils/dataset/_get_realcode_v2_metadata.py
repotest/utils/git/__init__.py
repotest/utils/git/_get_git_params.py
repotest/utils/git/git_diff_wrapper.py
repotest/utils/java/__init__.py
repotest/utils/java/java_test_fixer.py
repotest/utils/java/pom_file_fixer.py
repotest-uv-env/bin/activate_this.py
repositorytest-0.4.6.dist-info/METADATA
repositorytest-0.4.6.dist-info/WHEEL
repositorytest-0.4.6.dist-info/entry_points.txt
repositorytest-0.4.6.dist-info/top_level.txt
repositorytest-0.4.6.dist-info/RECORD
