Metadata-Version: 2.4
Name: repositorytest
Version: 0.4.6
Summary: A tool for cloning and testing repositories (docker or local, interface is the same).
Author-email: Pavel A <padamenko@gmail.com>
License-Expression: MIT
Project-URL: Homepage, https://github.com/MERA-Evaluation/repotest
Project-URL: Bug Tracker, https://github.com/MERA-Evaluation/repotest/issues
Classifier: Programming Language :: Python :: 3
Classifier: Programming Language :: Python :: 3.6
Classifier: Programming Language :: Python :: 3.7
Classifier: Programming Language :: Python :: 3.8
Classifier: Programming Language :: Python :: 3.9
Classifier: Programming Language :: Python :: 3.10
Classifier: Programming Language :: Python :: 3.11
Classifier: Programming Language :: Python :: 3.12
Requires-Python: >=3.6
License-File: LICENSE
Requires-Dist: docker
Requires-Dist: gitpython
Requires-Dist: tenacity>=9.0.0
Requires-Dist: python-dotenv
Requires-Dist: colorama==0.4.6
Requires-Dist: tqdm==4.67.1
Requires-Dist: psutil
Requires-Dist: fire>=0.6.0
Requires-Dist: ipython==8.12.2
Requires-Dist: coverage>=7.7.0
Provides-Extra: dev
Requires-Dist: setuptools; extra == "dev"
Requires-Dist: pytest; extra == "dev"
Requires-Dist: build; extra == "dev"
Requires-Dist: pandas>=2.0.0; extra == "dev"
Requires-Dist: pytest-json-report>=1.5.0; extra == "dev"
Requires-Dist: python-dotenv; extra == "dev"
Dynamic: license-file
